{
  "CM4001A": {
    "product": "CM4001A",
    "pdf": "CM4001A966-01.pdf",
    "chunks": 55,
    "tables": 7,
    "sections": [
      "Consulte “Función del comparador (COMP)” (p.16)",
      "EJEMPLO: mediciones en tableros de distribución (incluidos medidores secundarios), paneles",
      "El contenido del manual está sujeto a cambios, por ejemplo, debido a modificaciones en las",
      "Consulte “Retroiluminación de advertencia” (p.20)",
      "Ejemplo:",
      "Actualización del firmware del instrumento",
      "Función de retención (HOLD)",
      "**Retroiluminación**",
      "Consulte “Uso de GENNECT Cross” (p.21)",
      "**Función de retención (HOLD)**",
      "Si cambia del rango automático al modo MAX o MIN, el rango se fija en el rango actualmente",
      "**Realización de mediciones**",
      "**Función del comparador (COMP)**",
      "**Descripción del producto**",
      "Medición de la corriente de entrada (AC INRUSH)",
      "**Valores máx., mín., promedio y pico (MAX, MIN)**",
      "**Función de comunicación inalámbrica**",
      "Se pueden utilizar los siguientes dos métodos para medir la corriente de fuga:",
      "Función de registro de evento simple",
      "**Medición de la corriente de entrada (AC INRUSH)**"
    ]
  },
  "CM4002A": {
    "product": "CM4002A",
    "pdf": "CM4002A964-02_Manual_ES.pdf",
    "chunks": 221,
    "tables": 46,
    "sections": [
      "Se puede emitir el voltaje correspondiente al valor medido. (Procedimiento: p. 51)",
      "**2 Realizar una medición 31**",
      "Respete esta información de precaución para asegurarse de que el instrumento se utilice de",
      "Cuando la función de filtro está habilitada, el instrumento puede mostrar valores",
      "Retroiluminación",
      "1 [Quite el instrumento del objeto por medir y ]",
      "Identificación de eventos de activación de",
      "Especificaciones de medición, entrada y salida",
      "Si encuentra algún daño, póngase en contacto con su distribuidor o vendedor",
      "Función de ahorro automático de energía (APS)",
      "Valores máx., mín., promedio y pico (MAX/MIN)",
      "**3 Especifcaciones 67**",
      "Pase un paño seco suave con cuidado sobre las superficies del núcleo de las",
      "Dejar las abrazaderas abiertas provocará que el polvo o la suciedad se asienten",
      "Mantenga pulsada la tecla para",
      "Visite la página de preguntas frecuentes en el sitio web global de Hioki para obtener más",
      "Panel de visualización",
      "Puede descargar la versión más reciente del manual, así como",
      "4 Inicie el registro. 2 Establezca el rango (lectura",
      "El refresco de visualización puede Cuando el valor medido es estable, el refresco de"
    ]
  },
  "FT6380B": {
    "product": "FT6380B",
    "pdf": "FT6380B983-00.pdf",
    "chunks": 352,
    "tables": 20,
    "sections": [
      "Resistance Resistance measurement mode alarm: Beeps when measured",
      "Crest factor 5.0 or less (for the 60 A range, 1.7 or less)",
      "Si la resistencia de puesta a tierra del objetivo de medición se",
      "Auto-power-save Instrument automatically turns off approx. 5 min. after last key",
      "Verify that there is no foreign matter lodged between the tips of",
      "Storage",
      "Para borrar el último punto de dato",
      "Alarm Hi/Lo Separate Hi/Lo settings for resistance measurement and current",
      "Verifique que no haya materia extraña alojada entre las puntas",
      "Input Resistance range:",
      "Exposed to high temperature",
      "Cuando el flujo de corriente a través del cable de",
      "As illustrated below, the instrument is designed to measure",
      "Pressing any key while the alarm sounds will reset the time",
      "La retroiluminación se apagará automáticamente cuando no se",
      "The option listed below is available for the instrument. To order",
      "Refers to the displayed value of the measuring instrument. The limit values of reading",
      "To clear the last stored data point",
      "Antes de utilizar el instrumento por primera vez, instale dos pilas",
      "Efectos de la frecuencia Precisión × 0,3 (se especifica en la lista de precisión)"
    ]
  },
  "CM4371": {
    "product": "CM4371",
    "pdf": "hioki_CM4371-50_CM4373-50_CM4375-50_manual.pdf",
    "chunks": 250,
    "tables": 78,
    "sections": [
      "Respete esta información de precaución para asegurarse de que el instrumento se utilice de",
      "**5 Apéndice 113**",
      "P2000",
      "CM4371-",
      "Cuando se detecta CC:",
      "Valor",
      "Detector Cuerpo",
      "Instalación de las pilas y el adaptador inalámbrico Z3210",
      "Puede volver a activar la pantalla si",
      "Al recibir el instrumento, examínelo con detenimiento para asegurarse de que no ha sufrido",
      "Gracias por adquirir la pinza amperimétrica de CA/CC de Hioki CM4371-50/CM4373-50/",
      "Cuando comience otro registro de eventos, los",
      "La función de detección de voltaje no funciona correctamente en los siguientes circuitos y",
      "De lo contrario, el funcionamiento adecuado de los dispositivos médicos",
      "El perfil del dispositivo de interfaz humana (HID) con el que está equipado el adaptador",
      "Especificaciones generales",
      "Comprobación de continuidad",
      "Aproximadamente 20 horas (con el Z3210 instalado, con comunicación inalámbrica)",
      "Aunque una corriente detectada fluya a tierra",
      "**3 Especificaciones**"
    ]
  }
}